{
    "__TEXT1__": "Crafto - The Multipurpose HTML5 Template",
    "__TEXT2__": "Home",
    "__TEXT3__": "About",
    "__TEXT4__": "Expertise",
    "__TEXT5__": "Finance planning",
    "__TEXT6__": "Wealth management",
    "__TEXT7__": "Strategic planning",
    "__TEXT8__": "Audit assurance",
    "__TEXT9__": "Team",
    "__TEXT10__": "Pricing",
    "__TEXT11__": "News",
    "__TEXT12__": "Contact",
    "__TEXT13__": "Free quote",
    "__TEXT14__": "Looking for a finance agent?",
    "__TEXT15__": "How we can help you?",
    "__TEXT16__": "Send message",
    "__TEXT17__": "Pricing plans",
    "__TEXT18__": "Home",
    "__TEXT19__": "Pricing",
    "__TEXT20__": "Secure payments",
    "__TEXT21__": "Lorem ipsum is simply dummy text printing typesetting.",
    "__TEXT22__": "Money back guarantee",
    "__TEXT23__": "Lorem ipsum is simply dummy text printing typesetting.",
    "__TEXT24__": "Amazing price",
    "__TEXT25__": "Simple pricing",
    "__TEXT26__": "Basic",
    "__TEXT27__": "$19.99",
    "__TEXT28__": "monthly billing",
    "__TEXT29__": "Marketing strategy",
    "__TEXT30__": "Competitive work analysis",
    "__TEXT31__": "Social media share audit",
    "__TEXT32__": "Get started",
    "__TEXT33__": "Standard",
    "__TEXT34__": "$59.99",
    "__TEXT35__": "monthly billing",
    "__TEXT36__": "Marketing strategy",
    "__TEXT37__": "Competitive work analysis",
    "__TEXT38__": "Social media share audit",
    "__TEXT39__": "Monthly management",
    "__TEXT40__": "Get started",
    "__TEXT41__": "Premium",
    "__TEXT42__": "$99.99",
    "__TEXT43__": "monthly billing",
    "__TEXT44__": "Marketing strategy",
    "__TEXT45__": "Competitive work analysis",
    "__TEXT46__": "Social media share audit",
    "__TEXT47__": "Get started",
    "__TEXT48__": "Endless possibilities",
    "__TEXT49__": "Lorem ipsum is simply dummy printing typesetting industry.",
    "__TEXT50__": "Most commonly asked questions.",
    "__TEXT51__": "Can i try financial advice for free?",
    "__TEXT52__": "Lorem ipsum is simply dummy text of printing and typesetting industry lorem ipsum been dummy.",
    "__TEXT53__": "What are my payment options?",
    "__TEXT54__": "Lorem ipsum is simply dummy text of printing and typesetting industry lorem ipsum been dummy.",
    "__TEXT55__": "Is it safe to provide my credit card data?",
    "__TEXT56__": "Lorem ipsum is simply dummy text of printing and typesetting industry lorem ipsum been dummy.",
    "__TEXT57__": "Send message",
    "__TEXT58__": "We are trusted by more than 5000 very happy clients for finance services.",
    "__TEXT59__": "Company",
    "__TEXT60__": "About company",
    "__TEXT61__": "Company expertise",
    "__TEXT62__": "Creative people",
    "__TEXT63__": "Pricing plans",
    "__TEXT64__": "Customer",
    "__TEXT65__": "Company services",
    "__TEXT66__": "Company story",
    "__TEXT67__": "Latest news",
    "__TEXT68__": "Contact us",
    "__TEXT69__": "Subscribe newsletter",
    "__TEXT70__": "Subscribe our newsletter to get the latest news and updates.",
    "__TEXT71__": "Scroll"
}