{
    "__TEXT1__": "Crafto - The Multipurpose HTML5 Template",
    "__TEXT2__": "0222 8899900",
    "__TEXT3__": "Broadway, 24th Floor, San Francisco",
    "__TEXT4__": "Home",
    "__TEXT5__": "About",
    "__TEXT6__": "Destinations",
    "__TEXT7__": "India",
    "__TEXT8__": "42 Destinations",
    "__TEXT9__": "Poland",
    "__TEXT10__": "36 Destinations",
    "__TEXT11__": "Mexico",
    "__TEXT12__": "22 Destinations",
    "__TEXT13__": "Maldives",
    "__TEXT14__": "28 Destinations",
    "__TEXT15__": "tour packages",
    "__TEXT16__": "Tours",
    "__TEXT17__": "Reviews",
    "__TEXT18__": "Blog",
    "__TEXT19__": "Contact",
    "__TEXT20__": "×",
    "__TEXT21__": "What are you looking for?",
    "__TEXT22__": "Explore the world",
    "__TEXT23__": "World's leading travel agency",
    "__TEXT24__": "Get latest update for our trusted applications",
    "__TEXT25__": "$1200",
    "__TEXT26__": "Starting at",
    "__TEXT27__": "Africa wildlife",
    "__TEXT28__": "25Km from Madagascar",
    "__TEXT29__": "07 Days",
    "__TEXT30__": "Tour duration",
    "__TEXT31__": "Tripadvisor rating",
    "__TEXT32__": "Deluxe AC",
    "__TEXT33__": "WITH MEAL",
    "__TEXT34__": "Book holiday",
    "__TEXT35__": "$1600",
    "__TEXT36__": "Starting at",
    "__TEXT37__": "Morocco desert",
    "__TEXT38__": "48Km from Ouarzazate",
    "__TEXT39__": "03 Days",
    "__TEXT40__": "Tour duration",
    "__TEXT41__": "Tripadvisor rating",
    "__TEXT42__": "Classic AC",
    "__TEXT43__": "WITH MEAL",
    "__TEXT44__": "Book holiday",
    "__TEXT45__": "$1000",
    "__TEXT46__": "Starting at",
    "__TEXT47__": "Gunung rinjan",
    "__TEXT48__": "24Km from Indonesia",
    "__TEXT49__": "05 Days",
    "__TEXT50__": "Tour duration",
    "__TEXT51__": "Tripadvisor rating",
    "__TEXT52__": "Deluxe AC",
    "__TEXT53__": "WITH MEAL",
    "__TEXT54__": "Book holiday",
    "__TEXT55__": "Explore the world for yourself",
    "__TEXT56__": "Discover the world's leading travel agency.",
    "__TEXT57__": "Lorem ipsum is simply dummy text of the printing and typesetting industry. Lorem ipsum has been the industry's standard dummy text ever since.",
    "__TEXT58__": "About company",
    "__TEXT59__": "Discover tour",
    "__TEXT60__": "Superior service",
    "__TEXT61__": "Lorem ipsum text",
    "__TEXT62__": "Cheapest package",
    "__TEXT63__": "Lorem ipsum text",
    "__TEXT64__": "Greatest guides",
    "__TEXT65__": "Lorem ipsum text",
    "__TEXT66__": "Fully protected",
    "__TEXT67__": "Lorem ipsum text",
    "__TEXT68__": "Most popular tours",
    "__TEXT69__": "Popular packages",
    "__TEXT70__": "10 days",
    "__TEXT71__": "Majestic india life and great wildlife.",
    "__TEXT72__": "18 Reviews",
    "__TEXT73__": "08 days",
    "__TEXT74__": "$1200",
    "__TEXT75__": "Maldives resorts with return flights.",
    "__TEXT76__": "12 Reviews",
    "__TEXT77__": "05 days",
    "__TEXT78__": "Dubai parks resorts special packages.",
    "__TEXT79__": "10 Reviews",
    "__TEXT80__": "10 days",
    "__TEXT81__": "The everyday urban jungle of city.",
    "__TEXT82__": "16 Reviews",
    "__TEXT83__": "10 days",
    "__TEXT84__": "Majestic india life and great wildlife.",
    "__TEXT85__": "18 Reviews",
    "__TEXT86__": "08 days",
    "__TEXT87__": "$1200",
    "__TEXT88__": "Maldives resorts with return flights.",
    "__TEXT89__": "12 Reviews",
    "__TEXT90__": "05 days",
    "__TEXT91__": "Dubai parks resorts special packages.",
    "__TEXT92__": "10 Reviews",
    "__TEXT93__": "10 days",
    "__TEXT94__": "The everyday urban jungle of city.",
    "__TEXT95__": "16 Reviews",
    "__TEXT96__": "Authentic experiences",
    "__TEXT97__": "Prime destination",
    "__TEXT98__": "India",
    "__TEXT99__": "Poland",
    "__TEXT100__": "Mexico",
    "__TEXT101__": "Egypt",
    "__TEXT102__": "Africa",
    "__TEXT103__": "Kenya",
    "__TEXT104__": "Maldives",
    "__TEXT105__": "Dubai",
    "__TEXT106__": "World's hottest destinations for",
    "__TEXT107__": "Finding the perfect trips",
    "__TEXT108__": "Get ready to explore and discover your world.",
    "__TEXT109__": "Adventure",
    "__TEXT110__": "Friendly",
    "__TEXT111__": "Popular",
    "__TEXT112__": "Beaches",
    "__TEXT113__": "Honeymoon",
    "__TEXT114__": "Testimonials",
    "__TEXT115__": "Our happy traveller.",
    "__TEXT116__": "Alexander moore",
    "__TEXT117__": "Matthew taylor",
    "__TEXT118__": "Herman miller",
    "__TEXT119__": "Inspiring story",
    "__TEXT120__": "Travel blogs",
    "__TEXT121__": "It takes a real designer to design for real women",
    "__TEXT122__": "Experience breathtaking views and perspectives",
    "__TEXT123__": "Teamwork is essential for small teams to challenges",
    "__TEXT124__": "Get the amazing travel offers into your inbox!",
    "__TEXT125__": "Subscribe",
    "__TEXT126__": "crafto instagram",
    "__TEXT127__": "About",
    "__TEXT128__": "Destinations",
    "__TEXT129__": "Tours",
    "__TEXT130__": "Reviews",
    "__TEXT131__": "Blog",
    "__TEXT132__": "Contact",
    "__TEXT133__": "Scroll"
}